stats_can/__init__.py
stats_can/helpers.py
stats_can/sc.py
stats_can/schemas.py
stats_can/scwds.py
stats_can-3.1.0.dist-info/WHEEL
stats_can-3.1.0.dist-info/METADATA
stats_can-3.1.0.dist-info/RECORD
