Metadata-Version: 2.4
Name: stats-can
Version: 3.1.0
Summary: Read StatsCan data into python, mostly pandas dataframes
Keywords: statistics,Canada,data,API
Author: Ian Preston
License-Expression: GPL-3.0-or-later
Requires-Dist: requests
Requires-Dist: tqdm
Requires-Dist: pandas
Requires-Dist: numpy
Requires-Dist: pydantic>=2.9.2
Requires-Python: >=3.10, <4.0
Project-URL: Documentation, https://stats-can.readthedocs.io
Project-URL: Homepage, https://github.com/ianepreston/stats_can
Project-URL: Repository, https://github.com/ianepreston/stats_can
